CHANGELOG.md
LICENSE
MANIFEST.in
README.md
VERSION
pyproject.toml
setup.py
tests/test_cli.py
tests/test_config.py
tests/test_dot_notation.py
tests/test_errors.py
tests/test_integration.py
wl_config_manager/__init__.py
wl_config_manager/__main__.py
wl_config_manager/cli.py
wl_config_manager/config_manager.py
wl_config_manager/dot_notation.py
wl_config_manager/errors.py
wl_config_manager/log.py
wl_config_manager.egg-info/PKG-INFO
wl_config_manager.egg-info/SOURCES.txt
wl_config_manager.egg-info/dependency_links.txt
wl_config_manager.egg-info/entry_points.txt
wl_config_manager.egg-info/requires.txt
wl_config_manager.egg-info/top_level.txt