Metadata-Version: 2.4
Name: wl_config_manager
Version: 0.1.40
Summary: A flexible configuration manager for Python applications with .env support
Home-page: https://github.com/watkinslabs/config_manager
Author: Chris Watkins
Author-email: chris@watkinslabs.com
License: MIT
Project-URL: Bug Tracker, https://github.com/watkinslabs/config_manager/issues
Project-URL: Documentation, https://github.com/watkinslabs/config_manager
Project-URL: Source Code, https://github.com/watkinslabs/config_manager
Project-URL: Changelog, https://github.com/watkinslabs/config_manager/blob/main/CHANGELOG.md
Keywords: configuration config yaml json ini environment variables dotenv env settings
Classifier: Development Status :: 4 - Beta
Classifier: Intended Audience :: Developers
Classifier: License :: OSI Approved :: MIT License
Classifier: Programming Language :: Python :: 3
Classifier: Programming Language :: Python :: 3.6
Classifier: Programming Language :: Python :: 3.7
Classifier: Programming Language :: Python :: 3.8
Classifier: Programming Language :: Python :: 3.9
Classifier: Programming Language :: Python :: 3.10
Classifier: Programming Language :: Python :: 3.11
Classifier: Programming Language :: Python :: 3.12
Classifier: Operating System :: OS Independent
Classifier: Topic :: Software Development :: Libraries :: Python Modules
Classifier: Topic :: Software Development :: Libraries :: Application Frameworks
Classifier: Topic :: System :: Systems Administration
Requires-Python: >=3.6
License-File: LICENSE
Requires-Dist: pyyaml>=5.1
Provides-Extra: dev
Requires-Dist: pytest>=6.0; extra == "dev"
Requires-Dist: pytest-cov>=2.0; extra == "dev"
Requires-Dist: black>=21.0; extra == "dev"
Requires-Dist: flake8>=3.9; extra == "dev"
Requires-Dist: mypy>=0.9; extra == "dev"
Dynamic: author
Dynamic: author-email
Dynamic: classifier
Dynamic: description
Dynamic: description-content-type
Dynamic: home-page
Dynamic: keywords
Dynamic: license
Dynamic: license-file
Dynamic: project-url
Dynamic: provides-extra
Dynamic: requires-dist
Dynamic: requires-python
Dynamic: summary
